microjet
