Metadata-Version: 1.1
Name: MicroJet
Version: 0.0.4
Summary: Python 3 asynchronous microframework for microservices development
Home-page: https://github.com/ets-labs/python-microjet
Author: ETS Labs
Author-email: rmogilatov@gmail.com
License: BSD New
Platform: UNKNOWN
Classifier: Development Status :: 2 - Pre-Alpha
Classifier: Intended Audience :: Developers
Classifier: License :: OSI Approved :: BSD License
Classifier: Programming Language :: Python
Classifier: Programming Language :: Python :: 3
Classifier: Programming Language :: Python :: 3.4
Classifier: Programming Language :: Python :: 3.5
Classifier: Programming Language :: Python :: Implementation :: CPython
Classifier: Topic :: Software Development
Classifier: Topic :: Software Development :: Libraries
Classifier: Topic :: Software Development :: Libraries :: Python Modules
